{
  "git": {
    "changelog": "tsx scripts/generate-summary.ts npm",
    "commitMessage": "chore: release npm-v${version}",
    "tagName": "npm-v${version}"
  },
  "github": {
    "release": true,
    "releaseName": "npm-v${version}"
  },
  "npm": {
    "publish": false
  },
  "hooks": {
    "before:release": [
      "tsx scripts/check-npm-auth.ts"
    ],
    "after:bump": [
      "tsx scripts/open-changelog-editor.ts npm",
      "pnpm --filter pelelajs version ${version} --no-git-tag-version --no-git-checks",
      "pnpm run build"
    ],
    "after:release": [
      "pnpm --filter pelelajs publish --no-git-checks --access public",
      "echo \"✅ Successfully published npm-v${version} to NPM and GitHub!\""
    ]
  }
}
